{
    "docs": [
        "getting-started",
        "configuration",
        "writing-declarations",
        "compiler-annotations",
        "functions-and-the-self-parameter",
        "caveats",
        "editor-support",
        {
            "type": "category",
            "label": "API",
            "items": ["api/overview", "api/transformer", "api/printer", "api/plugins"]
        },
        {
            "type": "category",
            "label": "Contributors",
            "items": ["contributors/design-goals"]
        }
    ]
}
